{
  "source_file": "oprosnik_minaeva.xlsx",
  "level": "L3",
  "respondent": {
    "fio": "Минаева",
    "department": "Департамент развития взаимодействия с агентствами",
    "division": "Отдел по работе с ключевыми клиентами",
    "position": "Старший менеджер отдела по работе с ключевыми клиентами"
  },
  "tasks": [
    {
      "task_name": "Регистрирую новые агентства",
      "task_type": "Рутинная задача",
      "routine_level": "Высокий",
      "regularity": "Ежедневно",
      "time_minutes": 15,
      "task_character": "Ручной ввод данных",
      "problem": "Не успеваете",
      "problem_cause": "Нехватка времени",
      "interactions": [
        {
          "department": "Отдел клиентской поддержки",
          "description": "Девочки колл центра передают нам новые агентства, когда они отражаются в САМО, в самом начале"
        }
      ],
      "internal_resources": [
        "САМО",
        "битрикс"
      ],
      "external_resources": "гугл эксель",
      "priority": "3",
      "expected_results": "Сокращение времени выполнения",
      "risks": "Другое"
    },
    {
      "task_number": "2",
      "task_name": "Обрабатываю запросы от агентств",
      "task_type": "Рутинная задача",
      "routine_level": "Высокий",
      "regularity": "Ежедневно",
      "time_minutes": 15,
      "task_character": "Другое, обрабатываю письма,смс и голосовые по вопросам агентств, на один запрос уходит 5-10 мин, а дальше зависит от кол-ва звонков и смс",
      "problem": "Другое",
      "problem_cause": "Другое",
      "internal_resources": "почта",
      "external_resources": [
        "мессенджеры",
        "телефон"
      ],
      "priority": "2",
      "expected_results": "Повышение качества обслуживания клиентов"
    },
    {
      "task_number": "3",
      "task_name": "Набираю агентства на рекламные туры",
      "task_type": "Проблемная задача",
      "routine_level": "Средний",
      "regularity": "По запросу",
      "time_minutes": 60,
      "task_character": "Другое, время зависит от кол-во успешно зарегистрированных агентов в рекламный тур, и на сколько быстро рекламник набирается, бывает необходимо сделать дополнительные действия для набора в рекламный тур",
      "problem": "Другое",
      "problem_cause": "Другое",
      "interactions": [
        {
          "department": "Группа стран FIT",
          "description": "Получаем задачу по набору рекламного тура,кол-во, программа и тд в самом начале перед началом набора агентов на рекламный тур"
        },
        {
          "department": "Отдел контент-маркетинга",
          "description": "Просим создать картинку для набора рекламного тура, происходит это после получения информации рук-ей направлений, а так же публикуем на сайте информацию по рекламному туру и набору при запуске рекламного тура"
        },
        {
          "department": "Отдел группового бронирования",
          "description": "При необходимости аннулировать заявку, или скорректировать сумму обращаемся к менеджерам отджела бронирования"
        }
      ],
      "internal_resources": [
        "САМО",
        "гугл эксель",
        "наш сайт",
        "битрикс"
      ],
      "priority": "2"
    },
    {
      "task_number": "4",
      "task_name": "Набираю агентства на мероприятия",
      "task_type": "Рутинная задача",
      "routine_level": "Высокий",
      "regularity": "По запросу",
      "time_minutes": 60,
      "task_character": "Другое, здесь схоже с предыдущим пунктом",
      "problem": "Другое",
      "problem_cause": "Зависимость от других отделов",
      "interactions": [
        {
          "department": "Отдел рекламы",
          "description": "Получаем задачу по набору агентсв с информации по мероприятию"
        },
        {
          "department": "Отдел контент-маркетинга",
          "description": "Создаем картинку для набора агентств на мероприятие, так же публикуем информациию по мероприятию на сайте"
        }
      ],
      "internal_resources": [
        "САМО",
        "гугл эксель",
        "наш сайт",
        "битрикс"
      ],
      "priority": "2"
    },
    {
      "task_number": "5",
      "task_name": "Создаю rooming-list",
      "task_type": "Проблемная задача",
      "routine_level": "Высокий",
      "regularity": "По запросу",
      "time_minutes": 240,
      "task_character": "Ручной ввод данных",
      "problem": "Не успеваете",
      "problem_cause": "Нехватка времени",
      "interactions": [
        {
          "department": "Группа стран FIT",
          "description": "После подтверждения заявок, собираем с агентов необходимые документы и создаем руминг-где все в ручную заполняем (контакты,ФИО,аоллергии,почты и др) и вставляем сканы документов"
        }
      ],
      "internal_resources": [
        "САМО",
        "эксель",
        "почта"
      ],
      "priority": "3",
      "expected_results": "Освобождение времени для важных задач",
      "risks": "Другое"
    },
    {
      "task_number": "6",
      "task_name": "Проверяю договоры",
      "task_type": "Рутинная задача",
      "routine_level": "Средний",
      "regularity": "По запросу",
      "time_minutes": 5,
      "task_character": "Другое",
      "problem": "Другое",
      "problem_cause": "Другое",
      "interactions": [
        {
          "department": "Отдел клиентской поддержки",
          "description": "Когда агенты присылают нам догвоора (сканы) или оригиналы приносят -мы или колл центр принимают документы, проверяют и отмечают в САМО"
        }
      ],
      "internal_resources": [
        "САМО",
        "гугл эксель"
      ],
      "priority": "2"
    },
    {
      "task_number": "7",
      "task_name": "Слежу за оборотом агентств",
      "task_type": "Рутинная задача",
      "routine_level": "Средний",
      "regularity": "Еженедельно",
      "time_minutes": 10,
      "task_character": "Другое,здесь просто регулЯрный контроль работы агентств, при необходимости дополнительная стимуляция к их росту",
      "problem": "Другое",
      "problem_cause": "Другое",
      "internal_resources": "САМО",
      "priority": "2"
    },
    {
      "task_number": "8",
      "task_name": "Создаю дипломы по рекламным турам",
      "task_type": "Рутинная задача",
      "routine_level": "Средний",
      "regularity": "По запросу",
      "time_minutes": 30,
      "task_character": "Ручной ввод данных",
      "problem": "Трудно получить информацию",
      "problem_cause": "Отсутствие информации",
      "interactions": [
        {
          "department": "Отдел контент-маркетинга",
          "description": "Перед полетом нашего сопровождающего в рекламный тур-готовим дипломы для агентов, прописываем их фамилию и имя-и название агентсва-после чего отправляем дизайнерам на создание дипломоы и дальше передаем их сопровождающему"
        }
      ],
      "internal_resources": [
        "Битрикс",
        "САМО",
        "ворд"
      ],
      "priority": "2",
      "expected_results": "Освобождение времени для важных задач",
      "risks": "Другое"
    },
    {
      "task_number": "9",
      "task_name": "Веду личный телеграм канал куратора",
      "task_type": "Рутинная задача",
      "routine_level": "Средний",
      "regularity": "Ежедневно",
      "time_minutes": 40,
      "task_character": "Ручной ввод данных, здесь больше всего времени уходит на печатание дипломов",
      "problem": "Не успеваете",
      "problem_cause": "Нехватка времени",
      "external_resources": "телеграм",
      "priority": "2",
      "expected_results": "Повышение качества обслуживания клиентов"
    },
    {
      "task_number": "10",
      "task_name": "Вношу заявление на возвраты и переносы",
      "task_type": "Рутинная задача",
      "routine_level": "Средний",
      "regularity": "По запросу",
      "time_minutes": 10,
      "task_character": "Ручной ввод данных",
      "problem": "Другое",
      "problem_cause": "Другое",
      "interactions": [
        {
          "department": "Бухгалтерия",
          "description": "Проверяю правильность заполненного заявления, вставляю в реестр возвратов и перенос, отправляю письмо с  заявлением Ольге Лебедевой на почту"
        }
      ],
      "internal_resources": [
        "САМО",
        "гугл эксель"
      ],
      "priority": "3",
      "expected_results": "Другое",
      "risks": "Потеря контроля"
    },
    {
      "task_number": "11",
      "task_name": "Создаем картинку с рекламного тура",
      "task_type": "Рутинная задача",
      "routine_level": "Низкий",
      "regularity": "По запросу",
      "time_minutes": 10,
      "task_character": "Обработка изображений, просим сопровождающего из рекламного тура в первые дни прислать качественное общее фото с агентствами -на эту фотографию мы делаем рамку для фото с нашей символикой, и отправл сопровождающему, он(а) в свою очередь в крайний день на ужине присылает им в их чат",
      "problem": "Не дают информацию вовремя",
      "problem_cause": "Технические проблемы",
      "interactions": [
        {
          "department": "Отдел контент-маркетинга",
          "description": "После получения фотографии ставлю Алине задачу на создание рамки"
        }
      ],
      "internal_resources": "Битрикс",
      "external_resources": "мессенджеры",
      "priority": "2",
      "expected_results": "Повышение качества обслуживания клиентов"
    },
    {
      "task_number": "12",
      "task_name": "Встречаюсь с агентствами вне офиса",
      "task_type": "Рутинная задача",
      "routine_level": "Средний",
      "regularity": "Ежемесячно",
      "time_minutes": 240,
      "task_character": "Другое, езжу знакомиться с агентами, а так же если возникает необх поехать дополнительно к ним-чтобы закрыть какие-то вопросы по нам",
      "problem": "Другое",
      "problem_cause": "Другое",
      "internal_resources": "битрикс",
      "external_resources": "мессенджеры",
      "priority": "2",
      "expected_results": "Повышение качества обслуживания клиентов",
      "risks": "Нет рисков"
    },
    {
      "task_number": "🔵 Голубые ячейки",
      "task_name": "#NAME?"
    },
    {
      "task_number": "🟨 Желтые ячейки",
      "task_name": "#NAME?"
    }
  ]
}